neuralkg/__init__.py
neuralkg/data/DataPreprocess.py
neuralkg/data/Grounding.py
neuralkg/data/KGDataModule.py
neuralkg/data/RuleDataLoader.py
neuralkg/data/Sampler.py
neuralkg/data/__init__.py
neuralkg/data/base_data_module.py
neuralkg/eval_task/__init__.py
neuralkg/eval_task/link_prediction.py
neuralkg/lit_model/BaseLitModel.py
neuralkg/lit_model/CompGCNLitModel.py
neuralkg/lit_model/ConvELitModel.py
neuralkg/lit_model/CrossELitModel.py
neuralkg/lit_model/IterELitModel.py
neuralkg/lit_model/KBATLitModel.py
neuralkg/lit_model/KGELitModel.py
neuralkg/lit_model/RGCNLitModel.py
neuralkg/lit_model/RugELitModel.py
neuralkg/lit_model/XTransELitModel.py
neuralkg/lit_model/__init__.py
neuralkg/loss/Adv_Loss.py
neuralkg/loss/ComplEx_NNE_AER_Loss.py
neuralkg/loss/CrossE_Loss.py
neuralkg/loss/Cross_Entropy_Loss.py
neuralkg/loss/KBAT_Loss.py
neuralkg/loss/Margin_Loss.py
neuralkg/loss/RGCN_Loss.py
neuralkg/loss/RugE_Loss.py
neuralkg/loss/SimplE_Loss.py
neuralkg/loss/Softplus_Loss.py
neuralkg/loss/__init__.py
neuralkg/model/__init__.py
neuralkg/model/GNNModel/CompGCN.py
neuralkg/model/GNNModel/KBAT.py
neuralkg/model/GNNModel/RGCN.py
neuralkg/model/GNNModel/XTransE.py
neuralkg/model/GNNModel/__init__.py
neuralkg/model/KGEModel/BoxE.py
neuralkg/model/KGEModel/ComplEx.py
neuralkg/model/KGEModel/ConvE.py
neuralkg/model/KGEModel/CrossE.py
neuralkg/model/KGEModel/DistMult.py
neuralkg/model/KGEModel/DualE.py
neuralkg/model/KGEModel/HAKE.py
neuralkg/model/KGEModel/PairRE.py
neuralkg/model/KGEModel/RotatE.py
neuralkg/model/KGEModel/SimplE.py
neuralkg/model/KGEModel/TransE.py
neuralkg/model/KGEModel/TransH.py
neuralkg/model/KGEModel/TransR.py
neuralkg/model/KGEModel/__init__.py
neuralkg/model/KGEModel/model.py
neuralkg/model/RuleModel/ComplEx_NNE_AER.py
neuralkg/model/RuleModel/IterE.py
neuralkg/model/RuleModel/RugE.py
neuralkg/model/RuleModel/__init__.py
neuralkg/model/RuleModel/model.py
neuralkg/utils/__init__.py
neuralkg/utils/setup_parser.py
neuralkg/utils/tools.py
neuralkg-1.0.21.dist-info/LICENSE
neuralkg-1.0.21.dist-info/METADATA
neuralkg-1.0.21.dist-info/WHEEL
neuralkg-1.0.21.dist-info/top_level.txt
neuralkg-1.0.21.dist-info/RECORD
