Metadata-Version: 2.1
Name: neuralkg
Version: 1.0.21
Summary: An Open Source Library for Diverse Representation Learning of Knowledge Graphs
Home-page: https://github.com/zjukg/NeuralKG
Author: ZJUKG
Author-email: xnchen2020@zju.edu.cn
Classifier: Programming Language :: Python :: 3
Classifier: License :: OSI Approved :: MIT License
Classifier: Operating System :: OS Independent
Requires-Python: >=3.6
License-File: LICENSE
Requires-Dist: pytorch-lightning (==1.5.10)
Requires-Dist: PyYAML (>=6.0)
Requires-Dist: wandb (>=0.12.7)
Requires-Dist: IPython (>=5.0.0)
